LICENSE
MANIFEST.in
README.md
setup.py
penrose/__init__.py
penrose/defaults.py
penrose/version.py
penrose.egg-info/PKG-INFO
penrose.egg-info/SOURCES.txt
penrose.egg-info/dependency_links.txt
penrose.egg-info/entry_points.txt
penrose.egg-info/not-zip-safe
penrose.egg-info/requires.txt
penrose.egg-info/top_level.txt
penrose/client/__init__.py
penrose/client/install.py
penrose/client/list.py
penrose/logger/__init__.py
penrose/logger/message.py
penrose/logger/namer.py
penrose/logger/progress.py
penrose/logger/spinner.py
penrose/logger/__pycache__/__init__.cpython-36.pyc
penrose/logger/__pycache__/message.cpython-36.pyc
penrose/logger/__pycache__/namer.cpython-36.pyc
penrose/logger/__pycache__/progress.cpython-36.pyc
penrose/logger/__pycache__/spinner.cpython-36.pyc
penrose/main/__init__.py
penrose/main/library.py
penrose/main/validator/__init__.py
penrose/main/validator/library.py
penrose/main/validator/packages.py
penrose/main/validator/runtime.py
penrose/main/validator/utils.py
penrose/testing/__init__.py
penrose/testing/test_builder.sh
penrose/testing/test_client.py
penrose/testing/test_experiment.py
penrose/testing/data/not_an_experiment/experiment.js
penrose/testing/data/not_an_experiment/style.css
penrose/testing/data/test-task/config.json
penrose/testing/data/test-task/index.html
penrose/utils/__init__.py
penrose/utils/fileio.py